NooLite_F/Modules.py
NooLite_F/NooLiteFController.py
NooLite_F/Sensors.py
NooLite_F/Test.py
NooLite_F/__init__.py
NooLite_F/MTRF64/MTRF64Adapter.py
NooLite_F/MTRF64/MTRF64Controller.py
NooLite_F/MTRF64/__init__.py
NooLite_F-0.1.3.dist-info/LICENSE.txt
NooLite_F-0.1.3.dist-info/METADATA
NooLite_F-0.1.3.dist-info/WHEEL
NooLite_F-0.1.3.dist-info/top_level.txt
NooLite_F-0.1.3.dist-info/RECORD
