Metadata-Version: 2.1
Name: NooLite-F
Version: 0.1.3
Summary: Module to work with NooLite/NooLite-F modules via MTRF-64/MTRF-64-USB adapter
Home-page: https://github.com/SergejPr/NooLite-F
Author: Sergey Prytkov
Author-email: sergej.prytkov@gmail.com
License: MIT License
Keywords: noolite noolite-f noolitef
Platform: any
Classifier: Development Status :: 4 - Beta
Classifier: Intended Audience :: Developers
Classifier: Topic :: Software Development :: Libraries :: Python Modules
Classifier: Topic :: Home Automation
Classifier: Topic :: System :: Hardware
Classifier: License :: OSI Approved :: MIT License
Classifier: Programming Language :: Python :: 3.5
Classifier: Programming Language :: Python :: 3.6
Classifier: Programming Language :: Python :: 3.8
Classifier: Programming Language :: Python :: 3.9
License-File: LICENSE.txt
Requires-Dist: pyserial
